{"v":3,"stories":{"interactive-button--default":{"id":"interactive-button--default","title":"Interactive/Button","name":"Default","importPath":"./src/features/button/Button.stories.tsx"},"example-header--logged-in":{"id":"example-header--logged-in","title":"Example/Header","name":"Logged In","importPath":"./src/features/header/Header.stories.tsx"},"example-header--logged-out":{"id":"example-header--logged-out","title":"Example/Header","name":"Logged Out","importPath":"./src/features/header/Header.stories.tsx"},"example-page--logged-out":{"id":"example-page--logged-out","title":"Example/Page","name":"Logged Out","importPath":"./src/features/page/Page.stories.tsx"},"example-page--logged-in":{"id":"example-page--logged-in","title":"Example/Page","name":"Logged In","importPath":"./src/features/page/Page.stories.tsx"}}}
